exasol_integration_test_docker_environment/__init__.py
exasol_integration_test_docker_environment/abstract_method_exception.py
exasol_integration_test_docker_environment/certificate_resources/container/Dockerfile
exasol_integration_test_docker_environment/certificate_resources/container/create_certificates.sh
exasol_integration_test_docker_environment/certificate_resources/install_root_certificate.sh
exasol_integration_test_docker_environment/cli/__init__.py
exasol_integration_test_docker_environment/cli/cli.py
exasol_integration_test_docker_environment/cli/commands/__init__.py
exasol_integration_test_docker_environment/cli/commands/environment.py
exasol_integration_test_docker_environment/cli/commands/health.py
exasol_integration_test_docker_environment/cli/commands/spawn_test_environment.py
exasol_integration_test_docker_environment/cli/options/__init__.py
exasol_integration_test_docker_environment/cli/options/build_options.py
exasol_integration_test_docker_environment/cli/options/docker_repository_options.py
exasol_integration_test_docker_environment/cli/options/push_options.py
exasol_integration_test_docker_environment/cli/options/system_options.py
exasol_integration_test_docker_environment/cli/options/test_environment_options.py
exasol_integration_test_docker_environment/cli/termination_handler.py
exasol_integration_test_docker_environment/docker_db_config/2025.1.8/EXAConf
exasol_integration_test_docker_environment/docker_db_config/2025.1.8/init_db.sh
exasol_integration_test_docker_environment/docker_db_config/7.1.30/EXAConf
exasol_integration_test_docker_environment/docker_db_config/7.1.30/init_db.sh
exasol_integration_test_docker_environment/docker_db_config/8.29.13/EXAConf
exasol_integration_test_docker_environment/docker_db_config/8.29.13/init_db.sh
exasol_integration_test_docker_environment/doctor.py
exasol_integration_test_docker_environment/lib/__init__.py
exasol_integration_test_docker_environment/lib/api/__init__.py
exasol_integration_test_docker_environment-5.0.0.dist-info/LICENSE
exasol_integration_test_docker_environment-5.0.0.dist-info/METADATA
exasol_integration_test_docker_environment-5.0.0.dist-info/WHEEL
exasol_integration_test_docker_environment-5.0.0.dist-info/entry_points.txt
exasol_integration_test_docker_environment-5.0.0.dist-info/RECORD
