Metadata-Version: 2.3
Name: exasol-integration-test-docker-environment
Version: 5.0.0
Summary: Integration Test Docker Environment for Exasol
License: MIT
Keywords: exasol,docker,testing
Author: Torsten Kilias
Author-email: torsten.kilias@exasol.com
Requires-Python: >=3.10,<3.15
Classifier: License :: OSI Approved :: MIT License
Classifier: Programming Language :: Python :: 3
Classifier: Programming Language :: Python :: 3.10
Classifier: Programming Language :: Python :: 3.11
Classifier: Programming Language :: Python :: 3.12
Classifier: Programming Language :: Python :: 3.13
Requires-Dist: click (>=7.0)
Requires-Dist: docker (>=4.0.0,!=7.0.0) ; sys_platform != "win32"
Requires-Dist: docutils (>=0.21.2)
Requires-Dist: exasol-error-reporting (>=1.0.0,<2.0.0)
Requires-Dist: fabric (>=3.0.1,<4.0.0)
Requires-Dist: gitpython (>=2.1.0)
Requires-Dist: humanfriendly (>=4.18)
Requires-Dist: importlib_resources (>=5.4.0)
Requires-Dist: jinja2 (>=2.10.1)
Requires-Dist: jsonpickle (>=1.1)
Requires-Dist: luigi (>=2.8.4)
Requires-Dist: netaddr (>=0.7.19)
Requires-Dist: networkx (>=2.3)
Requires-Dist: portalocker (>=2.7.0,<3.0.0)
Requires-Dist: pydot (>=1.4.0)
Requires-Dist: requests (>=2.32.4)
Requires-Dist: simplejson (>=3.16.0)
Requires-Dist: stopwatch.py (>=1.0.0)
Project-URL: Homepage, https://github.com/exasol/integration-test-docker-environment
Project-URL: Repository, https://github.com/exasol/integration-test-docker-environment
